bitblock/__init__.py
bitblock/bitblock.async.bak.py
bitblock/bitblock.bak.py
bitblock/bitblock.py
bitblock/board_async.py
bitblock/board_control.py
bitblock/board_wrapper.py
bitblock/button.py
bitblock/cds.py
bitblock/constants.py
bitblock/dht.py
bitblock/led.py
bitblock/moisture.py
bitblock/motor.py
bitblock/oled.py
bitblock/pir.py
bitblock/poten.py
bitblock/rgb.py
bitblock/servo.py
bitblock/ultrasonic.py
bitblock/utils.py
pyblebb-1.8.5.dist-info/METADATA
pyblebb-1.8.5.dist-info/WHEEL
pyblebb-1.8.5.dist-info/top_level.txt
pyblebb-1.8.5.dist-info/RECORD
