Metadata-Version: 2.4
Name: pyblebb
Version: 1.8.5
Summary: A Python Library For BitBlock
Home-page: http://www.moyalab.com
Download-URL: https://www.moyalab.com
Author: devdio
Author-email: devdio.kei@gmail.com
License: GNU GPLv3
Keywords: Bitblock,Cocoboard,BBCar,Cocotics
Classifier: Intended Audience :: Education
Classifier: Operating System :: Microsoft :: Windows
Classifier: Programming Language :: Python :: 3.10
Classifier: Programming Language :: Python :: 3.11
Classifier: Programming Language :: Python :: 3.12
Classifier: Topic :: Education
Requires-Python: >=3.10
Requires-Dist: bleak==0.22.3
Requires-Dist: nest-asyncio==1.6.0
Requires-Dist: termcolor
Dynamic: author
Dynamic: author-email
Dynamic: classifier
Dynamic: description
Dynamic: description-content-type
Dynamic: download-url
Dynamic: home-page
Dynamic: keywords
Dynamic: license
Dynamic: requires-dist
Dynamic: requires-python
Dynamic: summary
